ja/__init__.py
ja/agg.py
ja/cli.py
ja/commands.py
ja/compose.py
ja/core.py
ja/export.py
ja/exporter.py
ja/expr.py
ja/group.py
ja/importer.py
ja/repl.py
ja/schema.py
ja/shell.py
ja/vfs.py
ja/window.py
jsonl_algebra-1.4.dist-info/licenses/LICENSE
jsonl_algebra-1.4.dist-info/METADATA
jsonl_algebra-1.4.dist-info/WHEEL
jsonl_algebra-1.4.dist-info/entry_points.txt
jsonl_algebra-1.4.dist-info/top_level.txt
jsonl_algebra-1.4.dist-info/RECORD
