Metadata-Version: 2.4
Name: jsonl-algebra
Version: 1.4
Summary: A powerful relational algebra CLI and library for JSONL data manipulation
Author-email: Alex Towell <lex@metafunctor.com>
License-Expression: MIT
Project-URL: Homepage, https://queelius.github.io/jsonl-algebra
Project-URL: Documentation, https://queelius.github.io/jsonl-algebra
Project-URL: Source, https://github.com/queelius/jsonl-algebra
Classifier: Development Status :: 4 - Beta
Classifier: Intended Audience :: Developers
Classifier: Intended Audience :: System Administrators
Classifier: Programming Language :: Python :: 3
Classifier: Programming Language :: Python :: 3.8
Classifier: Programming Language :: Python :: 3.9
Classifier: Programming Language :: Python :: 3.10
Classifier: Programming Language :: Python :: 3.11
Classifier: Programming Language :: Python :: 3.12
Classifier: Operating System :: OS Independent
Classifier: Topic :: Utilities
Classifier: Topic :: Text Processing :: Filters
Classifier: Topic :: Database
Classifier: Topic :: Software Development :: Libraries :: Python Modules
Requires-Python: >=3.8
License-File: LICENSE
Requires-Dist: jmespath
Requires-Dist: jsonschema
Requires-Dist: prompt-toolkit>=3.0
Requires-Dist: rich>=10.0
Provides-Extra: dev
Requires-Dist: pytest>=6.0; extra == "dev"
Requires-Dist: pytest-cov>=3.0; extra == "dev"
Requires-Dist: black>=22.0; extra == "dev"
Requires-Dist: isort>=5.0; extra == "dev"
Requires-Dist: flake8>=4.0; extra == "dev"
Requires-Dist: mypy>=0.950; extra == "dev"
Requires-Dist: bump2version>=1.0; extra == "dev"
Requires-Dist: twine>=3.0; extra == "dev"
Requires-Dist: build>=0.8; extra == "dev"
Requires-Dist: mkdocs>=1.4; extra == "dev"
Requires-Dist: mkdocs-material>=8.0; extra == "dev"
Requires-Dist: mkdocstrings[python]>=0.18; extra == "dev"
Provides-Extra: dataset
Requires-Dist: faker>=15.0; extra == "dataset"
Dynamic: license-file
